shopcloud_serverless/__init__.py
shopcloud_serverless/__main__.py
shopcloud_serverless/cli.py
shopcloud_serverless/configs.py
shopcloud_serverless/decorators.py
shopcloud_serverless/endpoints.py
shopcloud_serverless/endpoints_utils.py
shopcloud_serverless/exceptions.py
shopcloud_serverless/file_contents.py
shopcloud_serverless/gateways.py
shopcloud_serverless/helpers.py
shopcloud_serverless/jobs.py
shopcloud_serverless/steps.py
shopcloud_serverless-4.32.0.data/scripts/serverless
shopcloud_serverless-4.32.0.dist-info/LICENSE
shopcloud_serverless-4.32.0.dist-info/METADATA
shopcloud_serverless-4.32.0.dist-info/WHEEL
shopcloud_serverless-4.32.0.dist-info/top_level.txt
shopcloud_serverless-4.32.0.dist-info/RECORD
